Workbook

Sheet Übersicht
A1: FOX & PEOPLE — Personalcontrolling
A2: Verrechnung · Rückstellungen · DB1 — Geschäftsjahresübersicht (automatisch aus allen Blättern berechnet)
B5: GESAMTUMSATZ (JAHR) | E5: SELBSTKOSTEN (JAHR) | H5: RÜCKSTELLUNGEN (JAHR) | K5: DB1 GESAMT (JAHR) | N5: Ø DB1-MARGE
B6: =SUM(Verrechnung!P9:P108) | E6: =SUM(Selbstkosten!P9:P108) | H6: =SUM(Rückstellungen!AD9:AD108) | K6: =SUM(DB1!P9:P108) | N6: =IFERROR(SUM(DB1!P9:P108)/SUM(Verrechnung!P9:P108),0)
B7: Ø VERRECHNUNG / MITARBEITER | E7: PERSONALKOSTENQUOTE | H7: RÜCKSTELLUNGSQUOTE | K7: Ø DB1 / MITARBEITER | N7: MITARBEITER IM MINUS (ANZ.)
B8: =IFERROR(SUM(Verrechnung!P9:P108)/COUNTA(Stammdaten!C9:C108),0) | E8: =IFERROR(SUM(Selbstkosten!P9:P108)/SUM(Verrechnung!P9:P108),0) | H8: =IFERROR(SUM(Rückstellungen!AD9:AD108)/SUM(Verrechnung!P9:P108),0) | K8: =IFERROR(SUM(DB1!P9:P108)/COUNTA(Stammdaten!C9:C108),0) | N8: =COUNTIF(DB1!P9:P108,"<0")
B10: 🏆 TOP-PERFORMER — MITARBEITER NACH DB1 (JAHR) | H10: ⚠️ VERLUSTBRINGER — NEGATIVER DB1 IN DER ÜBERLASSUNG
B11: Rang | C11: Mitarbeiter | D11: Kunde | E11: DB1 Jahr | F11: Marge % | H11: Rang | I11: Mitarbeiter | J11: Kunde | K11: DB1 Jahr
B12: 1 | C12: =IFERROR(INDEX(DB1!$C$9:$C$108,MATCH(B12,DB1!$S$9:$S$108,0)),"") | D12: =IFERROR(INDEX(DB1!$B$9:$B$108,MATCH(B12,DB1!$S$9:$S$108,0)),"") | E12: =IFERROR(INDEX(DB1!$P$9:$P$108,MATCH(B12,DB1!$S$9:$S$108,0)),"") | F12: =IFERROR(INDEX(DB1!$R$9:$R$108,MATCH(B12,DB1!$S$9:$S$108,0)),"") | H12: 1 | I12: =IFERROR(INDEX(DB1!$C$9:$C$108,MATCH(H12,DB1!$T$9:$T$108,0)),"") | J12: =IFERROR(INDEX(DB1!$B$9:$B$108,MATCH(H12,DB1!$T$9:$T$108,0)),"") | K12: =IFERROR(INDEX(DB1!$P$9:$P$108,MATCH(H12,DB1!$T$9:$T$108,0)),"")
B13: 2 | C13: =IFERROR(INDEX(DB1!$C$9:$C$108,MATCH(B13,DB1!$S$9:$S$108,0)),"") | D13: =IFERROR(INDEX(DB1!$B$9:$B$108,MATCH(B13,DB1!$S$9:$S$108,0)),"") | E13: =IFERROR(INDEX(DB1!$P$9:$P$108,MATCH(B13,DB1!$S$9:$S$108,0)),"") | F13: =IFERROR(INDEX(DB1!$R$9:$R$108,MATCH(B13,DB1!$S$9:$S$108,0)),"") | H13: 2 | I13: =IFERROR(INDEX(DB1!$C$9:$C$108,MATCH(H13,DB1!$T$9:$T$108,0)),"") | J13: =IFERROR(INDEX(DB1!$B$9:$B$108,MATCH(H13,DB1!$T$9:$T$108,0)),"") | K13: =IFERROR(INDEX(DB1!$P$9:$P$108,MATCH(H13,DB1!$T$9:$T$108,0)),"")
B14: 3 | C14: =IFERROR(INDEX(DB1!$C$9:$C$108,MATCH(B14,DB1!$S$9:$S$108,0)),"") | D14: =IFERROR(INDEX(DB1!$B$9:$B$108,MATCH(B14,DB1!$S$9:$S$108,0)),"") | E14: =IFERROR(INDEX(DB1!$P$9:$P$108,MATCH(B14,DB1!$S$9:$S$108,0)),"") | F14: =IFERROR(INDEX(DB1!$R$9:$R$108,MATCH(B14,DB1!$S$9:$S$108,0)),"") | H14: 3 | I14: =IFERROR(INDEX(DB1!$C$9:$C$108,MATCH(H14,DB1!$T$9:$T$108,0)),"") | J14: =IFERROR(INDEX(DB1!$B$9:$B$108,MATCH(H14,DB1!$T$9:$T$108,0)),"") | K14: =IFERROR(INDEX(DB1!$P$9:$P$108,MATCH(H14,DB1!$T$9:$T$108,0)),"")
B15: 4 | C15: =IFERROR(INDEX(DB1!$C$9:$C$108,MATCH(B15,DB1!$S$9:$S$108,0)),"") | D15: =IFERROR(INDEX(DB1!$B$9:$B$108,MATCH(B15,DB1!$S$9:$S$108,0)),"") | E15: =IFERROR(INDEX(DB1!$P$9:$P$108,MATCH(B15,DB1!$S$9:$S$108,0)),"") | F15: =IFERROR(INDEX(DB1!$R$9:$R$108,MATCH(B15,DB1!$S$9:$S$108,0)),"") | H15: 4 | I15: =IFERROR(INDEX(DB1!$C$9:$C$108,MATCH(H15,DB1!$T$9:$T$108,0)),"") | J15: =IFERROR(INDEX(DB1!$B$9:$B$108,MATCH(H15,DB1!$T$9:$T$108,0)),"") | K15: =IFERROR(INDEX(DB1!$P$9:$P$108,MATCH(H15,DB1!$T$9:$T$108,0)),"")
B16: 5 | C16: =IFERROR(INDEX(DB1!$C$9:$C$108,MATCH(B16,DB1!$S$9:$S$108,0)),"") | D16: =IFERROR(INDEX(DB1!$B$9:$B$108,MATCH(B16,DB1!$S$9:$S$108,0)),"") | E16: =IFERROR(INDEX(DB1!$P$9:$P$108,MATCH(B16,DB1!$S$9:$S$108,0)),"") | F16: =IFERROR(INDEX(DB1!$R$9:$R$108,MATCH(B16,DB1!$S$9:$S$108,0)),"") | H16: 5 | I16: =IFERROR(INDEX(DB1!$C$9:$C$108,MATCH(H16,DB1!$T$9:$T$108,0)),"") | J16: =IFERROR(INDEX(DB1!$B$9:$B$108,MATCH(H16,DB1!$T$9:$T$108,0)),"") | K16: =IFERROR(INDEX(DB1!$P$9:$P$108,MATCH(H16,DB1!$T$9:$T$108,0)),"")
B17: 6 | C17: =IFERROR(INDEX(DB1!$C$9:$C$108,MATCH(B17,DB1!$S$9:$S$108,0)),"") | D17: =IFERROR(INDEX(DB1!$B$9:$B$108,MATCH(B17,DB1!$S$9:$S$108,0)),"") | E17: =IFERROR(INDEX(DB1!$P$9:$P$108,MATCH(B17,DB1!$S$9:$S$108,0)),"") | F17: =IFERROR(INDEX(DB1!$R$9:$R$108,MATCH(B17,DB1!$S$9:$S$108,0)),"") | H17: 6 | I17: =IFERROR(INDEX(DB1!$C$9:$C$108,MATCH(H17,DB1!$T$9:$T$108,0)),"") | J17: =IFERROR(INDEX(DB1!$B$9:$B$108,MATCH(H17,DB1!$T$9:$T$108,0)),"") | K17: =IFERROR(INDEX(DB1!$P$9:$P$108,MATCH(H17,DB1!$T$9:$T$108,0)),"")
B18: 7 | C18: =IFERROR(INDEX(DB1!$C$9:$C$108,MATCH(B18,DB1!$S$9:$S$108,0)),"") | D18: =IFERROR(INDEX(DB1!$B$9:$B$108,MATCH(B18,DB1!$S$9:$S$108,0)),"") | E18: =IFERROR(INDEX(DB1!$P$9:$P$108,MATCH(B18,DB1!$S$9:$S$108,0)),"") | F18: =IFERROR(INDEX(DB1!$R$9:$R$108,MATCH(B18,DB1!$S$9:$S$108,0)),"") | H18: 7 | I18: =IFERROR(INDEX(DB1!$C$9:$C$108,MATCH(H18,DB1!$T$9:$T$108,0)),"") | J18: =IFERROR(INDEX(DB1!$B$9:$B$108,MATCH(H18,DB1!$T$9:$T$108,0)),"") | K18: =IFERROR(INDEX(DB1!$P$9:$P$108,MATCH(H18,DB1!$T$9:$T$108,0)),"")
B19: 8 | C19: =IFERROR(INDEX(DB1!$C$9:$C$108,MATCH(B19,DB1!$S$9:$S$108,0)),"") | D19: =IFERROR(INDEX(DB1!$B$9:$B$108,MATCH(B19,DB1!$S$9:$S$108,0)),"") | E19: =IFERROR(INDEX(DB1!$P$9:$P$108,MATCH(B19,DB1!$S$9:$S$108,0)),"") | F19: =IFERROR(INDEX(DB1!$R$9:$R$108,MATCH(B19,DB1!$S$9:$S$108,0)),"") | H19: 8 | I19: =IFERROR(INDEX(DB1!$C$9:$C$108,MATCH(H19,DB1!$T$9:$T$108,0)),"") | J19: =IFERROR(INDEX(DB1!$B$9:$B$108,MATCH(H19,DB1!$T$9:$T$108,0)),"") | K19: =IFERROR(INDEX(DB1!$P$9:$P$108,MATCH(H19,DB1!$T$9:$T$108,0)),"")
B20: 9 | C20: =IFERROR(INDEX(DB1!$C$9:$C$108,MATCH(B20,DB1!$S$9:$S$108,0)),"") | D20: =IFERROR(INDEX(DB1!$B$9:$B$108,MATCH(B20,DB1!$S$9:$S$108,0)),"") | E20: =IFERROR(INDEX(DB1!$P$9:$P$108,MATCH(B20,DB1!$S$9:$S$108,0)),"") | F20: =IFERROR(INDEX(DB1!$R$9:$R$108,MATCH(B20,DB1!$S$9:$S$108,0)),"") | H20: 9 | I20: =IFERROR(INDEX(DB1!$C$9:$C$108,MATCH(H20,DB1!$T$9:$T$108,0)),"") | J20: =IFERROR(INDEX(DB1!$B$9:$B$108,MATCH(H20,DB1!$T$9:$T$108,0)),"") | K20: =IFERROR(INDEX(DB1!$P$9:$P$108,MATCH(H20,DB1!$T$9:$T$108,0)),"")
B21: 10 | C21: =IFERROR(INDEX(DB1!$C$9:$C$108,MATCH(B21,DB1!$S$9:$S$108,0)),"") | D21: =IFERROR(INDEX(DB1!$B$9:$B$108,MATCH(B21,DB1!$S$9:$S$108,0)),"") | E21: =IFERROR(INDEX(DB1!$P$9:$P$108,MATCH(B21,DB1!$S$9:$S$108,0)),"") | F21: =IFERROR(INDEX(DB1!$R$9:$R$108,MATCH(B21,DB1!$S$9:$S$108,0)),"") | H21: 10 | I21: =IFERROR(INDEX(DB1!$C$9:$C$108,MATCH(H21,DB1!$T$9:$T$108,0)),"") | J21: =IFERROR(INDEX(DB1!$B$9:$B$108,MATCH(H21,DB1!$T$9:$T$108,0)),"") | K21: =IFERROR(INDEX(DB1!$P$9:$P$108,MATCH(H21,DB1!$T$9:$T$108,0)),"")
B24: 🏢 KUNDEN-RANKING NACH DB1 (JAHR)
B25: Rang | C25: Kunde | E25: Verrechnung Jahr | F25: DB1 Jahr | G25: Marge %
B26: 1 | C26: =IFERROR(INDEX('Kunden-Auswertung'!$A$4:$A$13,MATCH(B26,'Kunden-Auswertung'!$G$4:$G$13,0)),"") | E26: =IFERROR(INDEX('Kunden-Auswertung'!$B$4:$B$13,MATCH(B26,'Kunden-Auswertung'!$G$4:$G$13,0)),"") | F26: =IFERROR(INDEX('Kunden-Auswertung'!$E$4:$E$13,MATCH(B26,'Kunden-Auswertung'!$G$4:$G$13,0)),"") | G26: =IFERROR(INDEX('Kunden-Auswertung'!$F$4:$F$13,MATCH(B26,'Kunden-Auswertung'!$G$4:$G$13,0)),"")
B27: 2 | C27: =IFERROR(INDEX('Kunden-Auswertung'!$A$4:$A$13,MATCH(B27,'Kunden-Auswertung'!$G$4:$G$13,0)),"") | E27: =IFERROR(INDEX('Kunden-Auswertung'!$B$4:$B$13,MATCH(B27,'Kunden-Auswertung'!$G$4:$G$13,0)),"") | F27: =IFERROR(INDEX('Kunden-Auswertung'!$E$4:$E$13,MATCH(B27,'Kunden-Auswertung'!$G$4:$G$13,0)),"") | G27: =IFERROR(INDEX('Kunden-Auswertung'!$F$4:$F$13,MATCH(B27,'Kunden-Auswertung'!$G$4:$G$13,0)),"")
B28: 3 | C28: =IFERROR(INDEX('Kunden-Auswertung'!$A$4:$A$13,MATCH(B28,'Kunden-Auswertung'!$G$4:$G$13,0)),"") | E28: =IFERROR(INDEX('Kunden-Auswertung'!$B$4:$B$13,MATCH(B28,'Kunden-Auswertung'!$G$4:$G$13,0)),"") | F28: =IFERROR(INDEX('Kunden-Auswertung'!$E$4:$E$13,MATCH(B28,'Kunden-Auswertung'!$G$4:$G$13,0)),"") | G28: =IFERROR(INDEX('Kunden-Auswertung'!$F$4:$F$13,MATCH(B28,'Kunden-Auswertung'!$G$4:$G$13,0)),"")
B29: 4 | C29: =IFERROR(INDEX('Kunden-Auswertung'!$A$4:$A$13,MATCH(B29,'Kunden-Auswertung'!$G$4:$G$13,0)),"") | E29: =IFERROR(INDEX('Kunden-Auswertung'!$B$4:$B$13,MATCH(B29,'Kunden-Auswertung'!$G$4:$G$13,0)),"") | F29: =IFERROR(INDEX('Kunden-Auswertung'!$E$4:$E$13,MATCH(B29,'Kunden-Auswertung'!$G$4:$G$13,0)),"") | G29: =IFERROR(INDEX('Kunden-Auswertung'!$F$4:$F$13,MATCH(B29,'Kunden-Auswertung'!$G$4:$G$13,0)),"")
B30: 5 | C30: =IFERROR(INDEX('Kunden-Auswertung'!$A$4:$A$13,MATCH(B30,'Kunden-Auswertung'!$G$4:$G$13,0)),"") | E30: =IFERROR(INDEX('Kunden-Auswertung'!$B$4:$B$13,MATCH(B30,'Kunden-Auswertung'!$G$4:$G$13,0)),"") | F30: =IFERROR(INDEX('Kunden-Auswertung'!$E$4:$E$13,MATCH(B30,'Kunden-Auswertung'!$G$4:$G$13,0)),"") | G30: =IFERROR(INDEX('Kunden-Auswertung'!$F$4:$F$13,MATCH(B30,'Kunden-Auswertung'!$G$4:$G$13,0)),"")
B31: 6 | C31: =IFERROR(INDEX('Kunden-Auswertung'!$A$4:$A$13,MATCH(B31,'Kunden-Auswertung'!$G$4:$G$13,0)),"") | E31: =IFERROR(INDEX('Kunden-Auswertung'!$B$4:$B$13,MATCH(B31,'Kunden-Auswertung'!$G$4:$G$13,0)),"") | F31: =IFERROR(INDEX('Kunden-Auswertung'!$E$4:$E$13,MATCH(B31,'Kunden-Auswertung'!$G$4:$G$13,0)),"") | G31: =IFERROR(INDEX('Kunden-Auswertung'!$F$4:$F$13,MATCH(B31,'Kunden-Auswertung'!$G$4:$G$13,0)),"")
B32: 7 | C32: =IFERROR(INDEX('Kunden-Auswertung'!$A$4:$A$13,MATCH(B32,'Kunden-Auswertung'!$G$4:$G$13,0)),"") | E32: =IFERROR(INDEX('Kunden-Auswertung'!$B$4:$B$13,MATCH(B32,'Kunden-Auswertung'!$G$4:$G$13,0)),"") | F32: =IFERROR(INDEX('Kunden-Auswertung'!$E$4:$E$13,MATCH(B32,'Kunden-Auswertung'!$G$4:$G$13,0)),"") | G32: =IFERROR(INDEX('Kunden-Auswertung'!$F$4:$F$13,MATCH(B32,'Kunden-Auswertung'!$G$4:$G$13,0)),"")
B33: 8 | C33: =IFERROR(INDEX('Kunden-Auswertung'!$A$4:$A$13,MATCH(B33,'Kunden-Auswertung'!$G$4:$G$13,0)),"") | E33: =IFERROR(INDEX('Kunden-Auswertung'!$B$4:$B$13,MATCH(B33,'Kunden-Auswertung'!$G$4:$G$13,0)),"") | F33: =IFERROR(INDEX('Kunden-Auswertung'!$E$4:$E$13,MATCH(B33,'Kunden-Auswertung'!$G$4:$G$13,0)),"") | G33: =IFERROR(INDEX('Kunden-Auswertung'!$F$4:$F$13,MATCH(B33,'Kunden-Auswertung'!$G$4:$G$13,0)),"")
B34: 9 | C34: =IFERROR(INDEX('Kunden-Auswertung'!$A$4:$A$13,MATCH(B34,'Kunden-Auswertung'!$G$4:$G$13,0)),"") | E34: =IFERROR(INDEX('Kunden-Auswertung'!$B$4:$B$13,MATCH(B34,'Kunden-Auswertung'!$G$4:$G$13,0)),"") | F34: =IFERROR(INDEX('Kunden-Auswertung'!$E$4:$E$13,MATCH(B34,'Kunden-Auswertung'!$G$4:$G$13,0)),"") | G34: =IFERROR(INDEX('Kunden-Auswertung'!$F$4:$F$13,MATCH(B34,'Kunden-Auswertung'!$G$4:$G$13,0)),"")
B35: 10 | C35: =IFERROR(INDEX('Kunden-Auswertung'!$A$4:$A$13,MATCH(B35,'Kunden-Auswertung'!$G$4:$G$13,0)),"") | E35: =IFERROR(INDEX('Kunden-Auswertung'!$B$4:$B$13,MATCH(B35,'Kunden-Auswertung'!$G$4:$G$13,0)),"") | F35: =IFERROR(INDEX('Kunden-Auswertung'!$E$4:$E$13,MATCH(B35,'Kunden-Auswertung'!$G$4:$G$13,0)),"") | G35: =IFERROR(INDEX('Kunden-Auswertung'!$F$4:$F$13,MATCH(B35,'Kunden-Auswertung'!$G$4:$G$13,0)),"")
B37: Hinweis: Kunden- und Mitarbeiternamen in 'Stammdaten' pflegen. Verrechnung & Selbstkosten monatlich in den jeweiligen Blättern eintragen — Rückstellungen und DB1 werden automatisch berechnet.
B58: 📈 MONATSENTWICKLUNG — UMSATZ, SELBSTKOSTEN, RÜCKSTELLUNGEN & DB1

Sheet Stammdaten
A1: STAMMDATEN — Kunden & Mitarbeiter
A2: Kunden- und Mitarbeiternamen selbst ausfüllen · Rückstellungssätze zentral festlegen
A4: Einstellungen · Rückstellungssätze
A5: Rückstellungssatz Urlaubsgeld (Anteil vom Monats-Selbstkostensatz) | C5: 0.083333333
A6: Rückstellungssatz Weihnachtsgeld (Anteil vom Monats-Selbstkostensatz) | C6: 0.083333333
A7: Eingabefeld (bitte ausfüllen)
A8: ID | B8: Kunde | C8: Mitarbeiter | D8: Rolle / Position
A9: 1 | B9: Alpina Logistik GmbH | C9: Julia Wagner | D9: Versandmitarbeiter
A10: 2 | B10: Alpina Logistik GmbH | C10: Jasmin Berger | D10: Versandmitarbeiter
A11: 3 | B11: Alpina Logistik GmbH | C11: Martin Reiter | D11: Versandmitarbeiter
A12: 4 | B12: Alpina Logistik GmbH | C12: Lisa Schwarz | D12: Kommissionierer
A13: 5 | B13: Alpina Logistik GmbH | C13: Katharina Hofer | D13: Staplerfahrer
A14: 6 | B14: Alpina Logistik GmbH | C14: Jasmin Huber | D14: Lagerlogistiker
A15: 7 | B15: Alpina Logistik GmbH | C15: Andreas Egger | D15: Kommissionierer
A16: 8 | B16: Alpina Logistik GmbH | C16: Alexander Winkler | D16: Versandmitarbeiter
A17: 9 | B17: Alpina Logistik GmbH | C17: Christian Egger | D17: Lagerlogistiker
A18: 10 | B18: Alpina Logistik GmbH | C18: Florian Winkler | D18: Lagerlogistiker
A19: 11 | B19: Bergmüller Bau AG | C19: Lena Auer | D19: Poliersassistent
A20: 12 | B20: Bergmüller Bau AG | C20: Laura Aigner | D20: Poliersassistent
... A108: 100 | B108: Jung Automotive Systems GmbH | C108: Georg Moser | D108: Fließbandmitarbeiter

Sheet Verrechnung
A1: VERRECHNUNG — Rechnungsbeträge an Kunden je Mitarbeiter
A2: Monatlich an den Kunden verrechneter Betrag (netto) je überlassenem Mitarbeiter eintragen.
A4: Verknüpfung aus Stammdaten | D4: Eingabefeld (bitte je Monat ausfüllen) | G4: Formel (Jahressumme)
A8: ID | B8: Kunde | C8: Mitarbeiter | D8: Jan | E8: Feb | F8: Mär | G8: Apr | H8: Mai | I8: Jun | J8: Jul | K8: Aug | L8: Sep | M8: Okt | N8: Nov | O8: Dez | P8: Summe Jahr
A9: =Stammdaten!A9 | B9: =Stammdaten!B9 | C9: =Stammdaten!C9 | D9: 4388.19 | E9: 4457.46 | F9: 4383.95 | G9: 4227.57 | H9: 4331.69 | I9: 4547.99 | J9: 4299.87 | K9: 4318.48 | L9: 4200.04 | M9: 4319.77 | N9: 4417.62 | O9: 3928.41 | P9: =SUM(D9:O9)
A10: =Stammdaten!A10 | B10: =Stammdaten!B10 | C10: =Stammdaten!C10 | D10: 4574.47 | E10: 4231.83 | F10: 4414.63 | G10: 4437.03 | H10: 4429.12 | I10: 4251.84 | J10: 3762.1 | K10: 4423.65 | L10: 4481.29 | M10: 4512.93 | N10: 4236.79 | O10: 4003.47 | P10: =SUM(D10:O10)
A11: =Stammdaten!A11 | B11: =Stammdaten!B11 | C11: =Stammdaten!C11 | D11: 6921.93 | E11: 6786.33 | F11: 6653.3 | G11: 6637.96 | H11: 6479.12 | I11: 6810.72 | J11: 5859.68 | K11: 6568.19 | L11: 6524.81 | M11: 6798.64 | N11: 6711.44 | O11: 6325.67 | P11: =SUM(D11:O11)
A12: =Stammdaten!A12 | B12: =Stammdaten!B12 | C12: =Stammdaten!C12 | D12: 4868.81 | E12: 4888.93 | F12: 4638 | G12: 4649.68 | H12: 4675.78 | I12: 4637.27 | J12: 4490.05 | K12: 4882.23 | L12: 4882.46 | M12: 4519.38 | N12: 4519.11 | O12: 3865.46 | P12: =SUM(D12:O12)
A13: =Stammdaten!A13 | B13: =Stammdaten!B13 | C13: =Stammdaten!C13 | D13: 6595.61 | E13: 6675.53 | F13: 6633.95 | G13: 6757.67 | H13: 6813.89 | I13: 6730.11 | J13: 6078.1 | K13: 6609.1 | L13: 6490.24 | M13: 6894.47 | N13: 6496.35 | O13: 5717.1 | P13: =SUM(D13:O13)
A14: =Stammdaten!A14 | B14: =Stammdaten!B14 | C14: =Stammdaten!C14 | D14: 3711.47 | E14: 3860.32 | F14: 3687.95 | G14: 3758.53 | H14: 3797.69 | I14: 3707.38 | J14: 3489.56 | K14: 3786.66 | L14: 3814.33 | M14: 3949.93 | N14: 3730.16 | O14: 3529.67 | P14: =SUM(D14:O14)
A15: =Stammdaten!A15 | B15: =Stammdaten!B15 | C15: =Stammdaten!C15 | D15: 6759.4 | E15: 6707.1 | F15: 6539.5 | G15: 6768.24 | H15: 7055.34 | I15: 7121.74 | J15: 6609.41 | K15: 7000.69 | L15: 7016.71 | M15: 6642.4 | N15: 6988.35 | O15: 6158.33 | P15: =SUM(D15:O15)
A16: =Stammdaten!A16 | B16: =Stammdaten!B16 | C16: =Stammdaten!C16 | D16: 5400.39 | E16: 5449.88 | F16: 5548.45 | G16: 5484.89 | H16: 5825.91 | I16: 5636.81 | J16: 5083.56 | K16: 5871.8 | L16: 5822.85 | M16: 5619.92 | N16: 5764.18 | O16: 5329.89 | P16: =SUM(D16:O16)
A17: =Stammdaten!A17 | B17: =Stammdaten!B17 | C17: =Stammdaten!C17 | D17: 6278.08 | E17: 6124.27 | F17: 6479.25 | G17: 6270.39 | H17: 6264.97 | I17: 6321.73 | J17: 6010.53 | K17: 6421.72 | L17: 6317.63 | M17: 6422.62 | N17: 6079.86 | O17: 5933.44 | P17: =SUM(D17:O17)
A18: =Stammdaten!A18 | B18: =Stammdaten!B18 | C18: =Stammdaten!C18 | D18: 5561.92 | E18: 5365.99 | F18: 5455.25 | G18: 5420.93 | H18: 5402.13 | I18: 5241.29 | J18: 4660.94 | K18: 5281 | L18: 5283.23 | M18: 5416.09 | N18: 5239.44 | O18: 5303.25 | P18: =SUM(D18:O18)
A19: =Stammdaten!A19 | B19: =Stammdaten!B19 | C19: =Stammdaten!C19 | D19: 4127.07 | E19: 4488.37 | F19: 4186.61 | G19: 4321.01 | H19: 4420.68 | I19: 4405.79 | J19: 3883.61 | K19: 4487.87 | L19: 4415.09 | M19: 4441.25 | N19: 4245.54 | O19: 3787.3 | P19: =SUM(D19:O19)
A20: =Stammdaten!A20 | B20: =Stammdaten!B20 | C20: =Stammdaten!C20 | D20: 3868.32 | E20: 3975.92 | F20: 4008.35 | G20: 4067.15 | H20: 4173.01 | I20: 3954.14 | J20: 3590.31 | K20: 3999.08 | L20: 4102.23 | M20: 4169.59 | N20: 3898.88 | O20: 3751.87 | P20: =SUM(D20:O20)
... A108: =Stammdaten!A108 | B108: =Stammdaten!B108 | C108: =Stammdaten!C108 | D108: 4066.86 | E108: 4079.78 | F108: 4148.54 | G108: 3959.56 | H108: 4140.38 | I108: 4215.61 | J108: 3961.01 | K108: 4077.85 | L108: 4138.91 | M108: 4085.04 | N108: 4223.43 | O108: 3915.1 | P108: =SUM(D108:O108)

Sheet Selbstkosten
A1: SELBSTKOSTEN — Ist-Kosten je Mitarbeiter nach Lohnüberweisung
A2: Tatsächliche Personalkosten (Lohn/Gehalt inkl. Lohnnebenkosten) je Mitarbeiter nach erfolgter Lohnüberweisung eintragen.
A4: Verknüpfung aus Stammdaten | D4: Eingabefeld (bitte je Monat ausfüllen) | G4: Formel (Jahressumme)
A8: ID | B8: Kunde | C8: Mitarbeiter | D8: Jan | E8: Feb | F8: Mär | G8: Apr | H8: Mai | I8: Jun | J8: Jul | K8: Aug | L8: Sep | M8: Okt | N8: Nov | O8: Dez | P8: Summe Jahr
A9: =Stammdaten!A9 | B9: =Stammdaten!B9 | C9: =Stammdaten!C9 | D9: 3261.68 | E9: 3504.32 | F9: 3432.84 | G9: 3255.1 | H9: 3279.41 | I9: 3481.59 | J9: 3299.5 | K9: 3279.33 | L9: 3153.35 | M9: 3320.66 | N9: 3373.39 | O9: 2934.1 | P9: =SUM(D9:O9)
A10: =Stammdaten!A10 | B10: =Stammdaten!B10 | C10: =Stammdaten!C10 | D10: 4030.29 | E10: 3739.69 | F10: 3685.29 | G10: 3855.34 | H10: 3800.46 | I10: 3603.7 | J10: 3327.19 | K10: 3686.09 | L10: 3941.31 | M10: 3836.83 | N10: 3626.78 | O10: 3356.29 | P10: =SUM(D10:O10)
A11: =Stammdaten!A11 | B11: =Stammdaten!B11 | C11: =Stammdaten!C11 | D11: 4034.53 | E11: 3990.05 | F11: 3927.38 | G11: 3828.75 | H11: 3858.5 | I11: 3926.12 | J11: 3551.17 | K11: 3962.51 | L11: 3725.3 | M11: 4115.47 | N11: 4013.6 | O11: 3737.14 | P11: =SUM(D11:O11)
A12: =Stammdaten!A12 | B12: =Stammdaten!B12 | C12: =Stammdaten!C12 | D12: 3233.83 | E12: 3108.11 | F12: 3077.69 | G12: 2972.65 | H12: 3114.87 | I12: 3104.9 | J12: 2836.96 | K12: 3079.07 | L12: 3124.51 | M12: 2996.74 | N12: 3009.89 | O12: 2567.64 | P12: =SUM(D12:O12)
A13: =Stammdaten!A13 | B13: =Stammdaten!B13 | C13: =Stammdaten!C13 | D13: 6986.64 | E13: 6806.15 | F13: 7052.04 | G13: 7321.87 | H13: 7349.54 | I13: 7088.62 | J13: 6465.63 | K13: 6809.58 | L13: 7043.6 | M13: 7343.89 | N13: 6664.36 | O13: 5931.04 | P13: =SUM(D13:O13)
A14: =Stammdaten!A14 | B14: =Stammdaten!B14 | C14: =Stammdaten!C14 | D14: 2438.1 | E14: 2494.66 | F14: 2456.18 | G14: 2515.92 | H14: 2524.66 | I14: 2473.97 | J14: 2370.54 | K14: 2465.81 | L14: 2446.29 | M14: 2699.42 | N14: 2544.83 | O14: 2300.82 | P14: =SUM(D14:O14)
A15: =Stammdaten!A15 | B15: =Stammdaten!B15 | C15: =Stammdaten!C15 | D15: 3878.91 | E15: 3941.03 | F15: 3877.07 | G15: 3788.12 | H15: 4168.16 | I15: 4245.43 | J15: 3937.96 | K15: 3980.96 | L15: 3986.92 | M15: 3782.72 | N15: 4125.53 | O15: 3468.9 | P15: =SUM(D15:O15)
A16: =Stammdaten!A16 | B16: =Stammdaten!B16 | C16: =Stammdaten!C16 | D16: 5624.57 | E16: 5893.53 | F16: 5799.35 | G16: 5881.95 | H16: 6068.18 | I16: 5832.69 | J16: 5510.26 | K16: 6085.57 | L16: 6251.92 | M16: 5734.04 | N16: 5944.68 | O16: 5563.85 | P16: =SUM(D16:O16)
A17: =Stammdaten!A17 | B17: =Stammdaten!B17 | C17: =Stammdaten!C17 | D17: 3553.38 | E17: 3491.89 | F17: 3666.64 | G17: 3643.04 | H17: 3649 | I17: 3668.06 | J17: 3485.21 | K17: 3730.16 | L17: 3686.33 | M17: 3597.15 | N17: 3385.82 | O17: 3351.26 | P17: =SUM(D17:O17)
A18: =Stammdaten!A18 | B18: =Stammdaten!B18 | C18: =Stammdaten!C18 | D18: 3641.98 | E18: 3487.34 | F18: 3618.51 | G18: 3583.13 | H18: 3596.31 | I18: 3430.57 | J18: 2955.47 | K18: 3525.62 | L18: 3508.27 | M18: 3391.53 | N18: 3494.88 | O18: 3328.29 | P18: =SUM(D18:O18)
A19: =Stammdaten!A19 | B19: =Stammdaten!B19 | C19: =Stammdaten!C19 | D19: 3250.06 | E19: 3647.53 | F19: 3412.26 | G19: 3463.42 | H19: 3456.62 | I19: 3580.83 | J19: 3198.53 | K19: 3585.67 | L19: 3422.09 | M19: 3447.76 | N19: 3450.54 | O19: 2968.17 | P19: =SUM(D19:O19)
A20: =Stammdaten!A20 | B20: =Stammdaten!B20 | C20: =Stammdaten!C20 | D20: 2240.57 | E20: 2326.3 | F20: 2284.88 | G20: 2401.67 | H20: 2452.64 | I20: 2321.51 | J20: 2137.55 | K20: 2261.2 | L20: 2375.27 | M20: 2393.77 | N20: 2207.42 | O20: 2213.2 | P20: =SUM(D20:O20)
... A108: =Stammdaten!A108 | B108: =Stammdaten!B108 | C108: =Stammdaten!C108 | D108: 3229.08 | E108: 3122.73 | F108: 3229.06 | G108: 3008.42 | H108: 3252.46 | I108: 3185.43 | J108: 3002.7 | K108: 3192.38 | L108: 3267.89 | M108: 3186.09 | N108: 3323.06 | O108: 3043.2 | P108: =SUM(D108:O108)

Sheet Rückstellungen
A1: RÜCKSTELLUNGEN — Urlaubs- & Weihnachtsgeld je Mitarbeiter
A2: Automatisch berechnet aus den Selbstkosten × Rückstellungssatz (siehe Stammdaten). Getrennt je Mitarbeiter und Kunde ausgewiesen.
A4: Verknüpfung | D4: Formel (auto-berechnet)
A5: Rückstellungssatz Urlaubsgeld: | D5: =Stammdaten!C5
A6: Rückstellungssatz Weihnachtsgeld: | D6: =Stammdaten!C6
D7: RÜCKSTELLUNG URLAUBSGELD | Q7: RÜCKSTELLUNG WEIHNACHTSGELD
A8: ID | B8: Kunde | C8: Mitarbeiter | D8: Jan | E8: Feb | F8: Mär | G8: Apr | H8: Mai | I8: Jun | J8: Jul | K8: Aug | L8: Sep | M8: Okt | N8: Nov | O8: Dez | P8: Summe | Q8: Jan | R8: Feb | S8: Mär | T8: Apr | U8: Mai | V8: Jun | W8: Jul | X8: Aug | Y8: Sep | Z8: Okt | AA8: Nov | AB8: Dez | AC8: Summe | AD8: Rückstellungen Gesamt
A9: =Stammdaten!A9 | B9: =Stammdaten!B9 | C9: =Stammdaten!C9 | D9: =Selbstkosten!D9*$D$5 | E9: =Selbstkosten!E9*$D$5 | F9: =Selbstkosten!F9*$D$5 | G9: =Selbstkosten!G9*$D$5 | H9: =Selbstkosten!H9*$D$5 | I9: =Selbstkosten!I9*$D$5 | J9: =Selbstkosten!J9*$D$5 | K9: =Selbstkosten!K9*$D$5 | ... O9: =Selbstkosten!O9*$D$5 | P9: =SUM(D9:O9) | Q9: =Selbstkosten!D9*$D$6 | R9: =Selbstkosten!E9*$D$6 | S9: =Selbstkosten!F9*$D$6 | T9: =Selbstkosten!G9*$D$6 | U9: =Selbstkosten!H9*$D$6 | V9: =Selbstkosten!I9*$D$6 | W9: =Selbstkosten!J9*$D$6 | X9: =Selbstkosten!K9*$D$6 | ... AB9: =Selbstkosten!O9*$D$6 | AC9: =SUM(Q9:AB9) | AD9: =P9+AC9
A10: =Stammdaten!A10 | B10: =Stammdaten!B10 | C10: =Stammdaten!C10 | D10: =Selbstkosten!D10*$D$5 | E10: =Selbstkosten!E10*$D$5 | F10: =Selbstkosten!F10*$D$5 | G10: =Selbstkosten!G10*$D$5 | H10: =Selbstkosten!H10*$D$5 | I10: =Selbstkosten!I10*$D$5 | J10: =Selbstkosten!J10*$D$5 | K10: =Selbstkosten!K10*$D$5 | ... O10: =Selbstkosten!O10*$D$5 | P10: =SUM(D10:O10) | Q10: =Selbstkosten!D10*$D$6 | R10: =Selbstkosten!E10*$D$6 | S10: =Selbstkosten!F10*$D$6 | T10: =Selbstkosten!G10*$D$6 | U10: =Selbstkosten!H10*$D$6 | V10: =Selbstkosten!I10*$D$6 | W10: =Selbstkosten!J10*$D$6 | X10: =Selbstkosten!K10*$D$6 | ... AB10: =Selbstkosten!O10*$D$6 | AC10: =SUM(Q10:AB10) | AD10: =P10+AC10
A11: =Stammdaten!A11 | B11: =Stammdaten!B11 | C11: =Stammdaten!C11 | D11: =Selbstkosten!D11*$D$5 | E11: =Selbstkosten!E11*$D$5 | F11: =Selbstkosten!F11*$D$5 | G11: =Selbstkosten!G11*$D$5 | H11: =Selbstkosten!H11*$D$5 | I11: =Selbstkosten!I11*$D$5 | J11: =Selbstkosten!J11*$D$5 | K11: =Selbstkosten!K11*$D$5 | ... O11: =Selbstkosten!O11*$D$5 | P11: =SUM(D11:O11) | Q11: =Selbstkosten!D11*$D$6 | R11: =Selbstkosten!E11*$D$6 | S11: =Selbstkosten!F11*$D$6 | T11: =Selbstkosten!G11*$D$6 | U11: =Selbstkosten!H11*$D$6 | V11: =Selbstkosten!I11*$D$6 | W11: =Selbstkosten!J11*$D$6 | X11: =Selbstkosten!K11*$D$6 | ... AB11: =Selbstkosten!O11*$D$6 | AC11: =SUM(Q11:AB11) | AD11: =P11+AC11
A12: =Stammdaten!A12 | B12: =Stammdaten!B12 | C12: =Stammdaten!C12 | D12: =Selbstkosten!D12*$D$5 | E12: =Selbstkosten!E12*$D$5 | F12: =Selbstkosten!F12*$D$5 | G12: =Selbstkosten!G12*$D$5 | H12: =Selbstkosten!H12*$D$5 | I12: =Selbstkosten!I12*$D$5 | J12: =Selbstkosten!J12*$D$5 | K12: =Selbstkosten!K12*$D$5 | ... O12: =Selbstkosten!O12*$D$5 | P12: =SUM(D12:O12) | Q12: =Selbstkosten!D12*$D$6 | R12: =Selbstkosten!E12*$D$6 | S12: =Selbstkosten!F12*$D$6 | T12: =Selbstkosten!G12*$D$6 | U12: =Selbstkosten!H12*$D$6 | V12: =Selbstkosten!I12*$D$6 | W12: =Selbstkosten!J12*$D$6 | X12: =Selbstkosten!K12*$D$6 | ... AB12: =Selbstkosten!O12*$D$6 | AC12: =SUM(Q12:AB12) | AD12: =P12+AC12
A13: =Stammdaten!A13 | B13: =Stammdaten!B13 | C13: =Stammdaten!C13 | D13: =Selbstkosten!D13*$D$5 | E13: =Selbstkosten!E13*$D$5 | F13: =Selbstkosten!F13*$D$5 | G13: =Selbstkosten!G13*$D$5 | H13: =Selbstkosten!H13*$D$5 | I13: =Selbstkosten!I13*$D$5 | J13: =Selbstkosten!J13*$D$5 | K13: =Selbstkosten!K13*$D$5 | ... O13: =Selbstkosten!O13*$D$5 | P13: =SUM(D13:O13) | Q13: =Selbstkosten!D13*$D$6 | R13: =Selbstkosten!E13*$D$6 | S13: =Selbstkosten!F13*$D$6 | T13: =Selbstkosten!G13*$D$6 | U13: =Selbstkosten!H13*$D$6 | V13: =Selbstkosten!I13*$D$6 | W13: =Selbstkosten!J13*$D$6 | X13: =Selbstkosten!K13*$D$6 | ... AB13: =Selbstkosten!O13*$D$6 | AC13: =SUM(Q13:AB13) | AD13: =P13+AC13
A14: =Stammdaten!A14 | B14: =Stammdaten!B14 | C14: =Stammdaten!C14 | D14: =Selbstkosten!D14*$D$5 | E14: =Selbstkosten!E14*$D$5 | F14: =Selbstkosten!F14*$D$5 | G14: =Selbstkosten!G14*$D$5 | H14: =Selbstkosten!H14*$D$5 | I14: =Selbstkosten!I14*$D$5 | J14: =Selbstkosten!J14*$D$5 | K14: =Selbstkosten!K14*$D$5 | ... O14: =Selbstkosten!O14*$D$5 | P14: =SUM(D14:O14) | Q14: =Selbstkosten!D14*$D$6 | R14: =Selbstkosten!E14*$D$6 | S14: =Selbstkosten!F14*$D$6 | T14: =Selbstkosten!G14*$D$6 | U14: =Selbstkosten!H14*$D$6 | V14: =Selbstkosten!I14*$D$6 | W14: =Selbstkosten!J14*$D$6 | X14: =Selbstkosten!K14*$D$6 | ... AB14: =Selbstkosten!O14*$D$6 | AC14: =SUM(Q14:AB14) | AD14: =P14+AC14
A15: =Stammdaten!A15 | B15: =Stammdaten!B15 | C15: =Stammdaten!C15 | D15: =Selbstkosten!D15*$D$5 | E15: =Selbstkosten!E15*$D$5 | F15: =Selbstkosten!F15*$D$5 | G15: =Selbstkosten!G15*$D$5 | H15: =Selbstkosten!H15*$D$5 | I15: =Selbstkosten!I15*$D$5 | J15: =Selbstkosten!J15*$D$5 | K15: =Selbstkosten!K15*$D$5 | ... O15: =Selbstkosten!O15*$D$5 | P15: =SUM(D15:O15) | Q15: =Selbstkosten!D15*$D$6 | R15: =Selbstkosten!E15*$D$6 | S15: =Selbstkosten!F15*$D$6 | T15: =Selbstkosten!G15*$D$6 | U15: =Selbstkosten!H15*$D$6 | V15: =Selbstkosten!I15*$D$6 | W15: =Selbstkosten!J15*$D$6 | X15: =Selbstkosten!K15*$D$6 | ... AB15: =Selbstkosten!O15*$D$6 | AC15: =SUM(Q15:AB15) | AD15: =P15+AC15
A16: =Stammdaten!A16 | B16: =Stammdaten!B16 | C16: =Stammdaten!C16 | D16: =Selbstkosten!D16*$D$5 | E16: =Selbstkosten!E16*$D$5 | F16: =Selbstkosten!F16*$D$5 | G16: =Selbstkosten!G16*$D$5 | H16: =Selbstkosten!H16*$D$5 | I16: =Selbstkosten!I16*$D$5 | J16: =Selbstkosten!J16*$D$5 | K16: =Selbstkosten!K16*$D$5 | ... O16: =Selbstkosten!O16*$D$5 | P16: =SUM(D16:O16) | Q16: =Selbstkosten!D16*$D$6 | R16: =Selbstkosten!E16*$D$6 | S16: =Selbstkosten!F16*$D$6 | T16: =Selbstkosten!G16*$D$6 | U16: =Selbstkosten!H16*$D$6 | V16: =Selbstkosten!I16*$D$6 | W16: =Selbstkosten!J16*$D$6 | X16: =Selbstkosten!K16*$D$6 | ... AB16: =Selbstkosten!O16*$D$6 | AC16: =SUM(Q16:AB16) | AD16: =P16+AC16
A17: =Stammdaten!A17 | B17: =Stammdaten!B17 | C17: =Stammdaten!C17 | D17: =Selbstkosten!D17*$D$5 | E17: =Selbstkosten!E17*$D$5 | F17: =Selbstkosten!F17*$D$5 | G17: =Selbstkosten!G17*$D$5 | H17: =Selbstkosten!H17*$D$5 | I17: =Selbstkosten!I17*$D$5 | J17: =Selbstkosten!J17*$D$5 | K17: =Selbstkosten!K17*$D$5 | ... O17: =Selbstkosten!O17*$D$5 | P17: =SUM(D17:O17) | Q17: =Selbstkosten!D17*$D$6 | R17: =Selbstkosten!E17*$D$6 | S17: =Selbstkosten!F17*$D$6 | T17: =Selbstkosten!G17*$D$6 | U17: =Selbstkosten!H17*$D$6 | V17: =Selbstkosten!I17*$D$6 | W17: =Selbstkosten!J17*$D$6 | X17: =Selbstkosten!K17*$D$6 | ... AB17: =Selbstkosten!O17*$D$6 | AC17: =SUM(Q17:AB17) | AD17: =P17+AC17
A18: =Stammdaten!A18 | B18: =Stammdaten!B18 | C18: =Stammdaten!C18 | D18: =Selbstkosten!D18*$D$5 | E18: =Selbstkosten!E18*$D$5 | F18: =Selbstkosten!F18*$D$5 | G18: =Selbstkosten!G18*$D$5 | H18: =Selbstkosten!H18*$D$5 | I18: =Selbstkosten!I18*$D$5 | J18: =Selbstkosten!J18*$D$5 | K18: =Selbstkosten!K18*$D$5 | ... O18: =Selbstkosten!O18*$D$5 | P18: =SUM(D18:O18) | Q18: =Selbstkosten!D18*$D$6 | R18: =Selbstkosten!E18*$D$6 | S18: =Selbstkosten!F18*$D$6 | T18: =Selbstkosten!G18*$D$6 | U18: =Selbstkosten!H18*$D$6 | V18: =Selbstkosten!I18*$D$6 | W18: =Selbstkosten!J18*$D$6 | X18: =Selbstkosten!K18*$D$6 | ... AB18: =Selbstkosten!O18*$D$6 | AC18: =SUM(Q18:AB18) | AD18: =P18+AC18
A19: =Stammdaten!A19 | B19: =Stammdaten!B19 | C19: =Stammdaten!C19 | D19: =Selbstkosten!D19*$D$5 | E19: =Selbstkosten!E19*$D$5 | F19: =Selbstkosten!F19*$D$5 | G19: =Selbstkosten!G19*$D$5 | H19: =Selbstkosten!H19*$D$5 | I19: =Selbstkosten!I19*$D$5 | J19: =Selbstkosten!J19*$D$5 | K19: =Selbstkosten!K19*$D$5 | ... O19: =Selbstkosten!O19*$D$5 | P19: =SUM(D19:O19) | Q19: =Selbstkosten!D19*$D$6 | R19: =Selbstkosten!E19*$D$6 | S19: =Selbstkosten!F19*$D$6 | T19: =Selbstkosten!G19*$D$6 | U19: =Selbstkosten!H19*$D$6 | V19: =Selbstkosten!I19*$D$6 | W19: =Selbstkosten!J19*$D$6 | X19: =Selbstkosten!K19*$D$6 | ... AB19: =Selbstkosten!O19*$D$6 | AC19: =SUM(Q19:AB19) | AD19: =P19+AC19
A20: =Stammdaten!A20 | B20: =Stammdaten!B20 | C20: =Stammdaten!C20 | D20: =Selbstkosten!D20*$D$5 | E20: =Selbstkosten!E20*$D$5 | F20: =Selbstkosten!F20*$D$5 | G20: =Selbstkosten!G20*$D$5 | H20: =Selbstkosten!H20*$D$5 | I20: =Selbstkosten!I20*$D$5 | J20: =Selbstkosten!J20*$D$5 | K20: =Selbstkosten!K20*$D$5 | ... O20: =Selbstkosten!O20*$D$5 | P20: =SUM(D20:O20) | Q20: =Selbstkosten!D20*$D$6 | R20: =Selbstkosten!E20*$D$6 | S20: =Selbstkosten!F20*$D$6 | T20: =Selbstkosten!G20*$D$6 | U20: =Selbstkosten!H20*$D$6 | V20: =Selbstkosten!I20*$D$6 | W20: =Selbstkosten!J20*$D$6 | X20: =Selbstkosten!K20*$D$6 | ... AB20: =Selbstkosten!O20*$D$6 | AC20: =SUM(Q20:AB20) | AD20: =P20+AC20
... A108: =Stammdaten!A108 | B108: =Stammdaten!B108 | C108: =Stammdaten!C108 | D108: =Selbstkosten!D108*$D$5 | E108: =Selbstkosten!E108*$D$5 | F108: =Selbstkosten!F108*$D$5 | G108: =Selbstkosten!G108*$D$5 | H108: =Selbstkosten!H108*$D$5 | I108: =Selbstkosten!I108*$D$5 | J108: =Selbstkosten!J108*$D$5 | K108: =Selbstkosten!K108*$D$5 | ... O108: =Selbstkosten!O108*$D$5 | P108: =SUM(D108:O108) | Q108: =Selbstkosten!D108*$D$6 | R108: =Selbstkosten!E108*$D$6 | S108: =Selbstkosten!F108*$D$6 | T108: =Selbstkosten!G108*$D$6 | U108: =Selbstkosten!H108*$D$6 | V108: =Selbstkosten!I108*$D$6 | W108: =Selbstkosten!J108*$D$6 | X108: =Selbstkosten!K108*$D$6 | ... AB108: =Selbstkosten!O108*$D$6 | AC108: =SUM(Q108:AB108) | AD108: =P108+AC108

Sheet DB1
A1: DB1-BERECHNUNG — Deckungsbeitrag 1 je Mitarbeiter
A2: DB1 = Verrechnung − Selbstkosten − Rückstellung Urlaubsgeld − Rückstellung Weihnachtsgeld
A4: Verknüpfung | D4: Formel (auto-berechnet) | G4: DB1 negativ | J4: DB1 stark positiv
A8: ID | B8: Kunde | C8: Mitarbeiter | D8: Jan | E8: Feb | F8: Mär | G8: Apr | H8: Mai | I8: Jun | J8: Jul | K8: Aug | L8: Sep | M8: Okt | N8: Nov | O8: Dez | P8: Summe DB1 Jahr | Q8: Verrechnung Jahr | R8: DB1-Marge % | S8: Rang (bester DB1) | T8: Rang (Verlust)
A9: =Stammdaten!A9 | B9: =Stammdaten!B9 | C9: =Stammdaten!C9 | D9: =Verrechnung!D9-Selbstkosten!D9-Rückstellungen!D9-Rückstellungen!Q9 | E9: =Verrechnung!E9-Selbstkosten!E9-Rückstellungen!E9-Rückstellungen!R9 | F9: =Verrechnung!F9-Selbstkosten!F9-Rückstellungen!F9-Rückstellungen!S9 | G9: =Verrechnung!G9-Selbstkosten!G9-Rückstellungen!G9-Rückstellungen!T9 | H9: =Verrechnung!H9-Selbstkosten!H9-Rückstellungen!H9-Rückstellungen!U9 | I9: =Verrechnung!I9-Selbstkosten!I9-Rückstellungen!I9-Rückstellungen!V9 | J9: =Verrechnung!J9-Selbstkosten!J9-Rückstellungen!J9-Rückstellungen!W9 | K9: =Verrechnung!K9-Selbstkosten!K9-Rückstellungen!K9-Rückstellungen!X9 | ... O9: =Verrechnung!O9-Selbstkosten!O9-Rückstellungen!O9-Rückstellungen!AB9 | P9: =SUM(D9:O9) | Q9: =Verrechnung!P9 | R9: =IFERROR(P9/Q9,0) | S9: =RANK(P9,$P$9:$P$108,0) | T9: =IF(P9<0,RANK(P9,$P$9:$P$108,1),"")
A10: =Stammdaten!A10 | B10: =Stammdaten!B10 | C10: =Stammdaten!C10 | D10: =Verrechnung!D10-Selbstkosten!D10-Rückstellungen!D10-Rückstellungen!Q10 | E10: =Verrechnung!E10-Selbstkosten!E10-Rückstellungen!E10-Rückstellungen!R10 | F10: =Verrechnung!F10-Selbstkosten!F10-Rückstellungen!F10-Rückstellungen!S10 | G10: =Verrechnung!G10-Selbstkosten!G10-Rückstellungen!G10-Rückstellungen!T10 | H10: =Verrechnung!H10-Selbstkosten!H10-Rückstellungen!H10-Rückstellungen!U10 | I10: =Verrechnung!I10-Selbstkosten!I10-Rückstellungen!I10-Rückstellungen!V10 | J10: =Verrechnung!J10-Selbstkosten!J10-Rückstellungen!J10-Rückstellungen!W10 | K10: =Verrechnung!K10-Selbstkosten!K10-Rückstellungen!K10-Rückstellungen!X10 | ... O10: =Verrechnung!O10-Selbstkosten!O10-Rückstellungen!O10-Rückstellungen!AB10 | P10: =SUM(D10:O10) | Q10: =Verrechnung!P10 | R10: =IFERROR(P10/Q10,0) | S10: =RANK(P10,$P$9:$P$108,0) | T10: =IF(P10<0,RANK(P10,$P$9:$P$108,1),"")
A11: =Stammdaten!A11 | B11: =Stammdaten!B11 | C11: =Stammdaten!C11 | D11: =Verrechnung!D11-Selbstkosten!D11-Rückstellungen!D11-Rückstellungen!Q11 | E11: =Verrechnung!E11-Selbstkosten!E11-Rückstellungen!E11-Rückstellungen!R11 | F11: =Verrechnung!F11-Selbstkosten!F11-Rückstellungen!F11-Rückstellungen!S11 | G11: =Verrechnung!G11-Selbstkosten!G11-Rückstellungen!G11-Rückstellungen!T11 | H11: =Verrechnung!H11-Selbstkosten!H11-Rückstellungen!H11-Rückstellungen!U11 | I11: =Verrechnung!I11-Selbstkosten!I11-Rückstellungen!I11-Rückstellungen!V11 | J11: =Verrechnung!J11-Selbstkosten!J11-Rückstellungen!J11-Rückstellungen!W11 | K11: =Verrechnung!K11-Selbstkosten!K11-Rückstellungen!K11-Rückstellungen!X11 | ... O11: =Verrechnung!O11-Selbstkosten!O11-Rückstellungen!O11-Rückstellungen!AB11 | P11: =SUM(D11:O11) | Q11: =Verrechnung!P11 | R11: =IFERROR(P11/Q11,0) | S11: =RANK(P11,$P$9:$P$108,0) | T11: =IF(P11<0,RANK(P11,$P$9:$P$108,1),"")
A12: =Stammdaten!A12 | B12: =Stammdaten!B12 | C12: =Stammdaten!C12 | D12: =Verrechnung!D12-Selbstkosten!D12-Rückstellungen!D12-Rückstellungen!Q12 | E12: =Verrechnung!E12-Selbstkosten!E12-Rückstellungen!E12-Rückstellungen!R12 | F12: =Verrechnung!F12-Selbstkosten!F12-Rückstellungen!F12-Rückstellungen!S12 | G12: =Verrechnung!G12-Selbstkosten!G12-Rückstellungen!G12-Rückstellungen!T12 | H12: =Verrechnung!H12-Selbstkosten!H12-Rückstellungen!H12-Rückstellungen!U12 | I12: =Verrechnung!I12-Selbstkosten!I12-Rückstellungen!I12-Rückstellungen!V12 | J12: =Verrechnung!J12-Selbstkosten!J12-Rückstellungen!J12-Rückstellungen!W12 | K12: =Verrechnung!K12-Selbstkosten!K12-Rückstellungen!K12-Rückstellungen!X12 | ... O12: =Verrechnung!O12-Selbstkosten!O12-Rückstellungen!O12-Rückstellungen!AB12 | P12: =SUM(D12:O12) | Q12: =Verrechnung!P12 | R12: =IFERROR(P12/Q12,0) | S12: =RANK(P12,$P$9:$P$108,0) | T12: =IF(P12<0,RANK(P12,$P$9:$P$108,1),"")
A13: =Stammdaten!A13 | B13: =Stammdaten!B13 | C13: =Stammdaten!C13 | D13: =Verrechnung!D13-Selbstkosten!D13-Rückstellungen!D13-Rückstellungen!Q13 | E13: =Verrechnung!E13-Selbstkosten!E13-Rückstellungen!E13-Rückstellungen!R13 | F13: =Verrechnung!F13-Selbstkosten!F13-Rückstellungen!F13-Rückstellungen!S13 | G13: =Verrechnung!G13-Selbstkosten!G13-Rückstellungen!G13-Rückstellungen!T13 | H13: =Verrechnung!H13-Selbstkosten!H13-Rückstellungen!H13-Rückstellungen!U13 | I13: =Verrechnung!I13-Selbstkosten!I13-Rückstellungen!I13-Rückstellungen!V13 | J13: =Verrechnung!J13-Selbstkosten!J13-Rückstellungen!J13-Rückstellungen!W13 | K13: =Verrechnung!K13-Selbstkosten!K13-Rückstellungen!K13-Rückstellungen!X13 | ... O13: =Verrechnung!O13-Selbstkosten!O13-Rückstellungen!O13-Rückstellungen!AB13 | P13: =SUM(D13:O13) | Q13: =Verrechnung!P13 | R13: =IFERROR(P13/Q13,0) | S13: =RANK(P13,$P$9:$P$108,0) | T13: =IF(P13<0,RANK(P13,$P$9:$P$108,1),"")
A14: =Stammdaten!A14 | B14: =Stammdaten!B14 | C14: =Stammdaten!C14 | D14: =Verrechnung!D14-Selbstkosten!D14-Rückstellungen!D14-Rückstellungen!Q14 | E14: =Verrechnung!E14-Selbstkosten!E14-Rückstellungen!E14-Rückstellungen!R14 | F14: =Verrechnung!F14-Selbstkosten!F14-Rückstellungen!F14-Rückstellungen!S14 | G14: =Verrechnung!G14-Selbstkosten!G14-Rückstellungen!G14-Rückstellungen!T14 | H14: =Verrechnung!H14-Selbstkosten!H14-Rückstellungen!H14-Rückstellungen!U14 | I14: =Verrechnung!I14-Selbstkosten!I14-Rückstellungen!I14-Rückstellungen!V14 | J14: =Verrechnung!J14-Selbstkosten!J14-Rückstellungen!J14-Rückstellungen!W14 | K14: =Verrechnung!K14-Selbstkosten!K14-Rückstellungen!K14-Rückstellungen!X14 | ... O14: =Verrechnung!O14-Selbstkosten!O14-Rückstellungen!O14-Rückstellungen!AB14 | P14: =SUM(D14:O14) | Q14: =Verrechnung!P14 | R14: =IFERROR(P14/Q14,0) | S14: =RANK(P14,$P$9:$P$108,0) | T14: =IF(P14<0,RANK(P14,$P$9:$P$108,1),"")
A15: =Stammdaten!A15 | B15: =Stammdaten!B15 | C15: =Stammdaten!C15 | D15: =Verrechnung!D15-Selbstkosten!D15-Rückstellungen!D15-Rückstellungen!Q15 | E15: =Verrechnung!E15-Selbstkosten!E15-Rückstellungen!E15-Rückstellungen!R15 | F15: =Verrechnung!F15-Selbstkosten!F15-Rückstellungen!F15-Rückstellungen!S15 | G15: =Verrechnung!G15-Selbstkosten!G15-Rückstellungen!G15-Rückstellungen!T15 | H15: =Verrechnung!H15-Selbstkosten!H15-Rückstellungen!H15-Rückstellungen!U15 | I15: =Verrechnung!I15-Selbstkosten!I15-Rückstellungen!I15-Rückstellungen!V15 | J15: =Verrechnung!J15-Selbstkosten!J15-Rückstellungen!J15-Rückstellungen!W15 | K15: =Verrechnung!K15-Selbstkosten!K15-Rückstellungen!K15-Rückstellungen!X15 | ... O15: =Verrechnung!O15-Selbstkosten!O15-Rückstellungen!O15-Rückstellungen!AB15 | P15: =SUM(D15:O15) | Q15: =Verrechnung!P15 | R15: =IFERROR(P15/Q15,0) | S15: =RANK(P15,$P$9:$P$108,0) | T15: =IF(P15<0,RANK(P15,$P$9:$P$108,1),"")
A16: =Stammdaten!A16 | B16: =Stammdaten!B16 | C16: =Stammdaten!C16 | D16: =Verrechnung!D16-Selbstkosten!D16-Rückstellungen!D16-Rückstellungen!Q16 | E16: =Verrechnung!E16-Selbstkosten!E16-Rückstellungen!E16-Rückstellungen!R16 | F16: =Verrechnung!F16-Selbstkosten!F16-Rückstellungen!F16-Rückstellungen!S16 | G16: =Verrechnung!G16-Selbstkosten!G16-Rückstellungen!G16-Rückstellungen!T16 | H16: =Verrechnung!H16-Selbstkosten!H16-Rückstellungen!H16-Rückstellungen!U16 | I16: =Verrechnung!I16-Selbstkosten!I16-Rückstellungen!I16-Rückstellungen!V16 | J16: =Verrechnung!J16-Selbstkosten!J16-Rückstellungen!J16-Rückstellungen!W16 | K16: =Verrechnung!K16-Selbstkosten!K16-Rückstellungen!K16-Rückstellungen!X16 | ... O16: =Verrechnung!O16-Selbstkosten!O16-Rückstellungen!O16-Rückstellungen!AB16 | P16: =SUM(D16:O16) | Q16: =Verrechnung!P16 | R16: =IFERROR(P16/Q16,0) | S16: =RANK(P16,$P$9:$P$108,0) | T16: =IF(P16<0,RANK(P16,$P$9:$P$108,1),"")
A17: =Stammdaten!A17 | B17: =Stammdaten!B17 | C17: =Stammdaten!C17 | D17: =Verrechnung!D17-Selbstkosten!D17-Rückstellungen!D17-Rückstellungen!Q17 | E17: =Verrechnung!E17-Selbstkosten!E17-Rückstellungen!E17-Rückstellungen!R17 | F17: =Verrechnung!F17-Selbstkosten!F17-Rückstellungen!F17-Rückstellungen!S17 | G17: =Verrechnung!G17-Selbstkosten!G17-Rückstellungen!G17-Rückstellungen!T17 | H17: =Verrechnung!H17-Selbstkosten!H17-Rückstellungen!H17-Rückstellungen!U17 | I17: =Verrechnung!I17-Selbstkosten!I17-Rückstellungen!I17-Rückstellungen!V17 | J17: =Verrechnung!J17-Selbstkosten!J17-Rückstellungen!J17-Rückstellungen!W17 | K17: =Verrechnung!K17-Selbstkosten!K17-Rückstellungen!K17-Rückstellungen!X17 | ... O17: =Verrechnung!O17-Selbstkosten!O17-Rückstellungen!O17-Rückstellungen!AB17 | P17: =SUM(D17:O17) | Q17: =Verrechnung!P17 | R17: =IFERROR(P17/Q17,0) | S17: =RANK(P17,$P$9:$P$108,0) | T17: =IF(P17<0,RANK(P17,$P$9:$P$108,1),"")
A18: =Stammdaten!A18 | B18: =Stammdaten!B18 | C18: =Stammdaten!C18 | D18: =Verrechnung!D18-Selbstkosten!D18-Rückstellungen!D18-Rückstellungen!Q18 | E18: =Verrechnung!E18-Selbstkosten!E18-Rückstellungen!E18-Rückstellungen!R18 | F18: =Verrechnung!F18-Selbstkosten!F18-Rückstellungen!F18-Rückstellungen!S18 | G18: =Verrechnung!G18-Selbstkosten!G18-Rückstellungen!G18-Rückstellungen!T18 | H18: =Verrechnung!H18-Selbstkosten!H18-Rückstellungen!H18-Rückstellungen!U18 | I18: =Verrechnung!I18-Selbstkosten!I18-Rückstellungen!I18-Rückstellungen!V18 | J18: =Verrechnung!J18-Selbstkosten!J18-Rückstellungen!J18-Rückstellungen!W18 | K18: =Verrechnung!K18-Selbstkosten!K18-Rückstellungen!K18-Rückstellungen!X18 | ... O18: =Verrechnung!O18-Selbstkosten!O18-Rückstellungen!O18-Rückstellungen!AB18 | P18: =SUM(D18:O18) | Q18: =Verrechnung!P18 | R18: =IFERROR(P18/Q18,0) | S18: =RANK(P18,$P$9:$P$108,0) | T18: =IF(P18<0,RANK(P18,$P$9:$P$108,1),"")
A19: =Stammdaten!A19 | B19: =Stammdaten!B19 | C19: =Stammdaten!C19 | D19: =Verrechnung!D19-Selbstkosten!D19-Rückstellungen!D19-Rückstellungen!Q19 | E19: =Verrechnung!E19-Selbstkosten!E19-Rückstellungen!E19-Rückstellungen!R19 | F19: =Verrechnung!F19-Selbstkosten!F19-Rückstellungen!F19-Rückstellungen!S19 | G19: =Verrechnung!G19-Selbstkosten!G19-Rückstellungen!G19-Rückstellungen!T19 | H19: =Verrechnung!H19-Selbstkosten!H19-Rückstellungen!H19-Rückstellungen!U19 | I19: =Verrechnung!I19-Selbstkosten!I19-Rückstellungen!I19-Rückstellungen!V19 | J19: =Verrechnung!J19-Selbstkosten!J19-Rückstellungen!J19-Rückstellungen!W19 | K19: =Verrechnung!K19-Selbstkosten!K19-Rückstellungen!K19-Rückstellungen!X19 | ... O19: =Verrechnung!O19-Selbstkosten!O19-Rückstellungen!O19-Rückstellungen!AB19 | P19: =SUM(D19:O19) | Q19: =Verrechnung!P19 | R19: =IFERROR(P19/Q19,0) | S19: =RANK(P19,$P$9:$P$108,0) | T19: =IF(P19<0,RANK(P19,$P$9:$P$108,1),"")
A20: =Stammdaten!A20 | B20: =Stammdaten!B20 | C20: =Stammdaten!C20 | D20: =Verrechnung!D20-Selbstkosten!D20-Rückstellungen!D20-Rückstellungen!Q20 | E20: =Verrechnung!E20-Selbstkosten!E20-Rückstellungen!E20-Rückstellungen!R20 | F20: =Verrechnung!F20-Selbstkosten!F20-Rückstellungen!F20-Rückstellungen!S20 | G20: =Verrechnung!G20-Selbstkosten!G20-Rückstellungen!G20-Rückstellungen!T20 | H20: =Verrechnung!H20-Selbstkosten!H20-Rückstellungen!H20-Rückstellungen!U20 | I20: =Verrechnung!I20-Selbstkosten!I20-Rückstellungen!I20-Rückstellungen!V20 | J20: =Verrechnung!J20-Selbstkosten!J20-Rückstellungen!J20-Rückstellungen!W20 | K20: =Verrechnung!K20-Selbstkosten!K20-Rückstellungen!K20-Rückstellungen!X20 | ... O20: =Verrechnung!O20-Selbstkosten!O20-Rückstellungen!O20-Rückstellungen!AB20 | P20: =SUM(D20:O20) | Q20: =Verrechnung!P20 | R20: =IFERROR(P20/Q20,0) | S20: =RANK(P20,$P$9:$P$108,0) | T20: =IF(P20<0,RANK(P20,$P$9:$P$108,1),"")
... A108: =Stammdaten!A108 | B108: =Stammdaten!B108 | C108: =Stammdaten!C108 | D108: =Verrechnung!D108-Selbstkosten!D108-Rückstellungen!D108-Rückstellungen!Q108 | E108: =Verrechnung!E108-Selbstkosten!E108-Rückstellungen!E108-Rückstellungen!R108 | F108: =Verrechnung!F108-Selbstkosten!F108-Rückstellungen!F108-Rückstellungen!S108 | G108: =Verrechnung!G108-Selbstkosten!G108-Rückstellungen!G108-Rückstellungen!T108 | H108: =Verrechnung!H108-Selbstkosten!H108-Rückstellungen!H108-Rückstellungen!U108 | I108: =Verrechnung!I108-Selbstkosten!I108-Rückstellungen!I108-Rückstellungen!V108 | J108: =Verrechnung!J108-Selbstkosten!J108-Rückstellungen!J108-Rückstellungen!W108 | K108: =Verrechnung!K108-Selbstkosten!K108-Rückstellungen!K108-Rückstellungen!X108 | ... O108: =Verrechnung!O108-Selbstkosten!O108-Rückstellungen!O108-Rückstellungen!AB108 | P108: =SUM(D108:O108) | Q108: =Verrechnung!P108 | R108: =IFERROR(P108/Q108,0) | S108: =RANK(P108,$P$9:$P$108,0) | T108: =IF(P108<0,RANK(P108,$P$9:$P$108,1),"")

Sheet Kunden-Auswertung
A1: HILFSBLATT — Kunden-Auswertung
A2: Automatisch berechnet aus den 10 Kunden-Blöcken je 10 Mitarbeiter · bitte nicht manuell bearbeiten
A3: Kunde | B3: Verrechnung Jahr | C3: Selbstkosten Jahr | D3: Rückstellungen Jahr | E3: DB1 Jahr | F3: DB1-Marge % | G3: Rang
A4: =Stammdaten!B9 | B4: =SUMIF(Verrechnung!$B$9:$B$108,$A4,Verrechnung!$P$9:$P$108) | C4: =SUMIF(Selbstkosten!$B$9:$B$108,$A4,Selbstkosten!$P$9:$P$108) | D4: =SUMIF(Rückstellungen!$B$9:$B$108,$A4,Rückstellungen!$AD$9:$AD$108) | E4: =SUMIF(DB1!$B$9:$B$108,$A4,DB1!$P$9:$P$108) | F4: =IFERROR(E4/B4,0) | G4: =RANK(E4,$E$4:$E$13,0)
A5: =Stammdaten!B19 | B5: =SUMIF(Verrechnung!$B$9:$B$108,$A5,Verrechnung!$P$9:$P$108) | C5: =SUMIF(Selbstkosten!$B$9:$B$108,$A5,Selbstkosten!$P$9:$P$108) | D5: =SUMIF(Rückstellungen!$B$9:$B$108,$A5,Rückstellungen!$AD$9:$AD$108) | E5: =SUMIF(DB1!$B$9:$B$108,$A5,DB1!$P$9:$P$108) | F5: =IFERROR(E5/B5,0) | G5: =RANK(E5,$E$4:$E$13,0)
A6: =Stammdaten!B29 | B6: =SUMIF(Verrechnung!$B$9:$B$108,$A6,Verrechnung!$P$9:$P$108) | C6: =SUMIF(Selbstkosten!$B$9:$B$108,$A6,Selbstkosten!$P$9:$P$108) | D6: =SUMIF(Rückstellungen!$B$9:$B$108,$A6,Rückstellungen!$AD$9:$AD$108) | E6: =SUMIF(DB1!$B$9:$B$108,$A6,DB1!$P$9:$P$108) | F6: =IFERROR(E6/B6,0) | G6: =RANK(E6,$E$4:$E$13,0)
A7: =Stammdaten!B39 | B7: =SUMIF(Verrechnung!$B$9:$B$108,$A7,Verrechnung!$P$9:$P$108) | C7: =SUMIF(Selbstkosten!$B$9:$B$108,$A7,Selbstkosten!$P$9:$P$108) | D7: =SUMIF(Rückstellungen!$B$9:$B$108,$A7,Rückstellungen!$AD$9:$AD$108) | E7: =SUMIF(DB1!$B$9:$B$108,$A7,DB1!$P$9:$P$108) | F7: =IFERROR(E7/B7,0) | G7: =RANK(E7,$E$4:$E$13,0)
A8: =Stammdaten!B49 | B8: =SUMIF(Verrechnung!$B$9:$B$108,$A8,Verrechnung!$P$9:$P$108) | C8: =SUMIF(Selbstkosten!$B$9:$B$108,$A8,Selbstkosten!$P$9:$P$108) | D8: =SUMIF(Rückstellungen!$B$9:$B$108,$A8,Rückstellungen!$AD$9:$AD$108) | E8: =SUMIF(DB1!$B$9:$B$108,$A8,DB1!$P$9:$P$108) | F8: =IFERROR(E8/B8,0) | G8: =RANK(E8,$E$4:$E$13,0)
A9: =Stammdaten!B59 | B9: =SUMIF(Verrechnung!$B$9:$B$108,$A9,Verrechnung!$P$9:$P$108) | C9: =SUMIF(Selbstkosten!$B$9:$B$108,$A9,Selbstkosten!$P$9:$P$108) | D9: =SUMIF(Rückstellungen!$B$9:$B$108,$A9,Rückstellungen!$AD$9:$AD$108) | E9: =SUMIF(DB1!$B$9:$B$108,$A9,DB1!$P$9:$P$108) | F9: =IFERROR(E9/B9,0) | G9: =RANK(E9,$E$4:$E$13,0)
A10: =Stammdaten!B69 | B10: =SUMIF(Verrechnung!$B$9:$B$108,$A10,Verrechnung!$P$9:$P$108) | C10: =SUMIF(Selbstkosten!$B$9:$B$108,$A10,Selbstkosten!$P$9:$P$108) | D10: =SUMIF(Rückstellungen!$B$9:$B$108,$A10,Rückstellungen!$AD$9:$AD$108) | E10: =SUMIF(DB1!$B$9:$B$108,$A10,DB1!$P$9:$P$108) | F10: =IFERROR(E10/B10,0) | G10: =RANK(E10,$E$4:$E$13,0)
A11: =Stammdaten!B79 | B11: =SUMIF(Verrechnung!$B$9:$B$108,$A11,Verrechnung!$P$9:$P$108) | C11: =SUMIF(Selbstkosten!$B$9:$B$108,$A11,Selbstkosten!$P$9:$P$108) | D11: =SUMIF(Rückstellungen!$B$9:$B$108,$A11,Rückstellungen!$AD$9:$AD$108) | E11: =SUMIF(DB1!$B$9:$B$108,$A11,DB1!$P$9:$P$108) | F11: =IFERROR(E11/B11,0) | G11: =RANK(E11,$E$4:$E$13,0)
A12: =Stammdaten!B89 | B12: =SUMIF(Verrechnung!$B$9:$B$108,$A12,Verrechnung!$P$9:$P$108) | C12: =SUMIF(Selbstkosten!$B$9:$B$108,$A12,Selbstkosten!$P$9:$P$108) | D12: =SUMIF(Rückstellungen!$B$9:$B$108,$A12,Rückstellungen!$AD$9:$AD$108) | E12: =SUMIF(DB1!$B$9:$B$108,$A12,DB1!$P$9:$P$108) | F12: =IFERROR(E12/B12,0) | G12: =RANK(E12,$E$4:$E$13,0)
A13: =Stammdaten!B99 | B13: =SUMIF(Verrechnung!$B$9:$B$108,$A13,Verrechnung!$P$9:$P$108) | C13: =SUMIF(Selbstkosten!$B$9:$B$108,$A13,Selbstkosten!$P$9:$P$108) | D13: =SUMIF(Rückstellungen!$B$9:$B$108,$A13,Rückstellungen!$AD$9:$AD$108) | E13: =SUMIF(DB1!$B$9:$B$108,$A13,DB1!$P$9:$P$108) | F13: =IFERROR(E13/B13,0) | G13: =RANK(E13,$E$4:$E$13,0)
A16: Monatsentwicklung — Gesamt aller Mitarbeiter
A17: Monat | B17: Verrechnung | C17: Selbstkosten | D17: Rückstellungen | E17: DB1 | F17: DB1-Marge %
A18: Jan | B18: =SUM(Verrechnung!D$9:D$108) | C18: =SUM(Selbstkosten!D$9:D$108) | D18: =SUM(Rückstellungen!D$9:D$108)+SUM(Rückstellungen!Q$9:Q$108) | E18: =B18-C18-D18 | F18: =IFERROR(E18/B18,0)
A19: Feb | B19: =SUM(Verrechnung!E$9:E$108) | C19: =SUM(Selbstkosten!E$9:E$108) | D19: =SUM(Rückstellungen!E$9:E$108)+SUM(Rückstellungen!R$9:R$108) | E19: =B19-C19-D19 | F19: =IFERROR(E19/B19,0)
A20: Mär | B20: =SUM(Verrechnung!F$9:F$108) | C20: =SUM(Selbstkosten!F$9:F$108) | D20: =SUM(Rückstellungen!F$9:F$108)+SUM(Rückstellungen!S$9:S$108) | E20: =B20-C20-D20 | F20: =IFERROR(E20/B20,0)
A21: Apr | B21: =SUM(Verrechnung!G$9:G$108) | C21: =SUM(Selbstkosten!G$9:G$108) | D21: =SUM(Rückstellungen!G$9:G$108)+SUM(Rückstellungen!T$9:T$108) | E21: =B21-C21-D21 | F21: =IFERROR(E21/B21,0)
A22: Mai | B22: =SUM(Verrechnung!H$9:H$108) | C22: =SUM(Selbstkosten!H$9:H$108) | D22: =SUM(Rückstellungen!H$9:H$108)+SUM(Rückstellungen!U$9:U$108) | E22: =B22-C22-D22 | F22: =IFERROR(E22/B22,0)
A23: Jun | B23: =SUM(Verrechnung!I$9:I$108) | C23: =SUM(Selbstkosten!I$9:I$108) | D23: =SUM(Rückstellungen!I$9:I$108)+SUM(Rückstellungen!V$9:V$108) | E23: =B23-C23-D23 | F23: =IFERROR(E23/B23,0)
A24: Jul | B24: =SUM(Verrechnung!J$9:J$108) | C24: =SUM(Selbstkosten!J$9:J$108) | D24: =SUM(Rückstellungen!J$9:J$108)+SUM(Rückstellungen!W$9:W$108) | E24: =B24-C24-D24 | F24: =IFERROR(E24/B24,0)
A25: Aug | B25: =SUM(Verrechnung!K$9:K$108) | C25: =SUM(Selbstkosten!K$9:K$108) | D25: =SUM(Rückstellungen!K$9:K$108)+SUM(Rückstellungen!X$9:X$108) | E25: =B25-C25-D25 | F25: =IFERROR(E25/B25,0)
A26: Sep | B26: =SUM(Verrechnung!L$9:L$108) | C26: =SUM(Selbstkosten!L$9:L$108) | D26: =SUM(Rückstellungen!L$9:L$108)+SUM(Rückstellungen!Y$9:Y$108) | E26: =B26-C26-D26 | F26: =IFERROR(E26/B26,0)
A27: Okt | B27: =SUM(Verrechnung!M$9:M$108) | C27: =SUM(Selbstkosten!M$9:M$108) | D27: =SUM(Rückstellungen!M$9:M$108)+SUM(Rückstellungen!Z$9:Z$108) | E27: =B27-C27-D27 | F27: =IFERROR(E27/B27,0)
A28: Nov | B28: =SUM(Verrechnung!N$9:N$108) | C28: =SUM(Selbstkosten!N$9:N$108) | D28: =SUM(Rückstellungen!N$9:N$108)+SUM(Rückstellungen!AA$9:AA$108) | E28: =B28-C28-D28 | F28: =IFERROR(E28/B28,0)
A29: Dez | B29: =SUM(Verrechnung!O$9:O$108) | C29: =SUM(Selbstkosten!O$9:O$108) | D29: =SUM(Rückstellungen!O$9:O$108)+SUM(Rückstellungen!AB$9:AB$108) | E29: =B29-C29-D29 | F29: =IFERROR(E29/B29,0)
